pyflux_influxdb/__init__.py
pyflux_influxdb/flux.py
pyflux_influxdb/type_convert.py
test/__init__.py
test/test_flux.py
test/test_influxdb_client.py
pyflux_influxdb-1.1.0.dist-info/METADATA
pyflux_influxdb-1.1.0.dist-info/WHEEL
pyflux_influxdb-1.1.0.dist-info/top_level.txt
pyflux_influxdb-1.1.0.dist-info/RECORD
